Workbook

Sheet Assumptions
A1: SAGALABS FINANCIAL MODEL - ASSUMPTIONS
A2: Yellow cells are editable - change them to see impact on projections
A4: RAISE DETAILS
A5: Raise Amount (SEK) | B5: 35000000
A6: Dilution (%) | B6: 0.2
A7: Pre-Money Valuation | B7: =B5/B6-B5
A8: Post-Money Valuation | B8: =B5/B6
A10: SALARY COSTS (SWEDEN)
A11: Avg Base Salary (SEK/month) | B11: 90000
A12: Arbetsgivaravgift (%) | B12: 0.32
A13: Total Cost per Employee | B13: =B11*(1+B12) | C13: =Base * (1 + Avgift)
A15: PRICING
A16: Monthly License Fee (SEK) | B16: 100000
A17: Annual Contract Value | B17: =B16*12
A19: OPERATING COSTS
A20: Compute - Base (SEK/month) | B20: 50000
A21: Compute - Per Customer | B21: 12000
A22: Data - Base (SEK/month) | B22: 80000
A23: Data - Per Customer | B23: 5000
A24: Infrastructure - Base | B24: 25000
A25: Infrastructure - Per Employee | B25: 3000
A26: Office - Per Employee | B26: 6000
A27: Sales/Marketing - Base | B27: 30000
A28: Sales/Marketing - Per Customer | B28: 5000
A29: Admin & Legal - Base | B29: 25000
A30: Buffer (%) | B30: 0.1

Sheet Inputs
A1: MONTHLY INPUTS - Edit these to change projections
A3: Month | B3: M1 | C3: M2 | D3: M3 | E3: M4 | F3: M5 | G3: M6 | H3: M7 | I3: M8 | J3: M9 | K3: M10 | L3: M11 | M3: M12 | N3: M13 | O3: M14 | P3: M15 | Q3: M16 | R3: M17 | S3: M18 | T3: M19 | U3: M20 | V3: M21 | W3: M22 | X3: M23 | Y3: M24
A4: New Customers | B4: 0 | C4: 0 | D4: 0 | E4: 0 | F4: 1 | G4: 1 | H4: 1 | I4: 2 | J4: 2 | K4: 2 | L4: 3 | M4: 3 | N4: 3 | O4: 4 | P4: 4 | Q4: 4 | R4: 5 | S4: 5 | T4: 5 | U4: 6 | V4: 6 | W4: 6 | X4: 7 | Y4: 7
A5: Total Customers | B5: =B4 | C5: =B5+C4 | D5: =C5+D4 | E5: =D5+E4 | F5: =E5+F4 | G5: =F5+G4 | H5: =G5+H4 | I5: =H5+I4 | J5: =I5+J4 | ... Y5: =X5+Y4
A7: Team Size | B7: 4 | C7: 5 | D7: 6 | E7: 7 | F7: 8 | G7: 9 | H7: 10 | I7: 11 | J7: 12 | K7: 13 | L7: 14 | M7: 15 | N7: 17 | O7: 19 | P7: 21 | Q7: 23 | R7: 25 | S7: 26 | T7: 27 | U7: 28 | V7: 29 | W7: 30 | X7: 30 | Y7: 30

Sheet Cashflow
A1: 24-MONTH CASH FLOW - All values are formulas linked to Assumptions & Inputs
A3: Category | B3: M1 | C3: M2 | D3: M3 | E3: M4 | F3: M5 | G3: M6 | H3: M7 | I3: M8 | J3: M9 | K3: M10 | L3: M11 | M3: M12 | N3: M13 | O3: M14 | P3: M15 | Q3: M16 | R3: M17 | S3: M18 | T3: M19 | U3: M20 | V3: M21 | W3: M22 | X3: M23 | Y3: M24 | Z3: TOTAL/END
A4: CUSTOMERS
A5: New Customers | B5: =Inputs!B4 | C5: =Inputs!C4 | D5: =Inputs!D4 | E5: =Inputs!E4 | F5: =Inputs!F4 | G5: =Inputs!G4 | H5: =Inputs!H4 | I5: =Inputs!I4 | ... Y5: =Inputs!Y4 | Z5: =SUM(B5:Y5)
A6: Total Customers | B6: =Inputs!B5 | C6: =Inputs!C5 | D6: =Inputs!D5 | E6: =Inputs!E5 | F6: =Inputs!F5 | G6: =Inputs!G5 | H6: =Inputs!H5 | I6: =Inputs!I5 | ... Y6: =Inputs!Y5 | Z6: =Y6
A8: REVENUE
A9: Monthly Revenue | B9: =B6*Assumptions!$B$16 | C9: =C6*Assumptions!$B$16 | D9: =D6*Assumptions!$B$16 | E9: =E6*Assumptions!$B$16 | F9: =F6*Assumptions!$B$16 | G9: =G6*Assumptions!$B$16 | H9: =H6*Assumptions!$B$16 | I9: =I6*Assumptions!$B$16 | ... Y9: =Y6*Assumptions!$B$16 | Z9: =SUM(B9:Y9)
A10: ARR (Run Rate) | B10: =B9*12 | C10: =C9*12 | D10: =D9*12 | E10: =E9*12 | F10: =F9*12 | G10: =G9*12 | H10: =H9*12 | I10: =I9*12 | ... Y10: =Y9*12 | Z10: =Y10
A12: TEAM
A13: Team Size | B13: =Inputs!B7 | C13: =Inputs!C7 | D13: =Inputs!D7 | E13: =Inputs!E7 | F13: =Inputs!F7 | G13: =Inputs!G7 | H13: =Inputs!H7 | I13: =Inputs!I7 | ... Y13: =Inputs!Y7 | Z13: =Y13
A15: EXPENSES
A16: Salaries (incl. avgift) | B16: =B13*Assumptions!$B$13 | C16: =C13*Assumptions!$B$13 | D16: =D13*Assumptions!$B$13 | E16: =E13*Assumptions!$B$13 | F16: =F13*Assumptions!$B$13 | G16: =G13*Assumptions!$B$13 | H16: =H13*Assumptions!$B$13 | I16: =I13*Assumptions!$B$13 | ... Y16: =Y13*Assumptions!$B$13 | Z16: =SUM(B16:Y16)
A17: Compute | B17: =Assumptions!$B$20+(B6*Assumptions!$B$21) | C17: =Assumptions!$B$20+(C6*Assumptions!$B$21) | D17: =Assumptions!$B$20+(D6*Assumptions!$B$21) | E17: =Assumptions!$B$20+(E6*Assumptions!$B$21) | F17: =Assumptions!$B$20+(F6*Assumptions!$B$21) | G17: =Assumptions!$B$20+(G6*Assumptions!$B$21) | H17: =Assumptions!$B$20+(H6*Assumptions!$B$21) | I17: =Assumptions!$B$20+(I6*Assumptions!$B$21) | ... Y17: =Assumptions!$B$20+(Y6*Assumptions!$B$21) | Z17: =SUM(B17:Y17)
A18: Data | B18: =Assumptions!$B$22+(B6*Assumptions!$B$23) | C18: =Assumptions!$B$22+(C6*Assumptions!$B$23) | D18: =Assumptions!$B$22+(D6*Assumptions!$B$23) | E18: =Assumptions!$B$22+(E6*Assumptions!$B$23) | F18: =Assumptions!$B$22+(F6*Assumptions!$B$23) | G18: =Assumptions!$B$22+(G6*Assumptions!$B$23) | H18: =Assumptions!$B$22+(H6*Assumptions!$B$23) | I18: =Assumptions!$B$22+(I6*Assumptions!$B$23) | ... Y18: =Assumptions!$B$22+(Y6*Assumptions!$B$23) | Z18: =SUM(B18:Y18)
A19: Infrastructure | B19: =Assumptions!$B$24+(B13*Assumptions!$B$25) | C19: =Assumptions!$B$24+(C13*Assumptions!$B$25) | D19: =Assumptions!$B$24+(D13*Assumptions!$B$25) | E19: =Assumptions!$B$24+(E13*Assumptions!$B$25) | F19: =Assumptions!$B$24+(F13*Assumptions!$B$25) | G19: =Assumptions!$B$24+(G13*Assumptions!$B$25) | H19: =Assumptions!$B$24+(H13*Assumptions!$B$25) | I19: =Assumptions!$B$24+(I13*Assumptions!$B$25) | ... Y19: =Assumptions!$B$24+(Y13*Assumptions!$B$25) | Z19: =SUM(B19:Y19)
A20: Office | B20: =B13*Assumptions!$B$26 | C20: =C13*Assumptions!$B$26 | D20: =D13*Assumptions!$B$26 | E20: =E13*Assumptions!$B$26 | F20: =F13*Assumptions!$B$26 | G20: =G13*Assumptions!$B$26 | H20: =H13*Assumptions!$B$26 | I20: =I13*Assumptions!$B$26 | ... Y20: =Y13*Assumptions!$B$26 | Z20: =SUM(B20:Y20)
A21: Sales & Marketing | B21: =Assumptions!$B$27+(B6*Assumptions!$B$28) | C21: =Assumptions!$B$27+(C6*Assumptions!$B$28) | D21: =Assumptions!$B$27+(D6*Assumptions!$B$28) | E21: =Assumptions!$B$27+(E6*Assumptions!$B$28) | F21: =Assumptions!$B$27+(F6*Assumptions!$B$28) | G21: =Assumptions!$B$27+(G6*Assumptions!$B$28) | H21: =Assumptions!$B$27+(H6*Assumptions!$B$28) | I21: =Assumptions!$B$27+(I6*Assumptions!$B$28) | ... Y21: =Assumptions!$B$27+(Y6*Assumptions!$B$28) | Z21: =SUM(B21:Y21)
A22: Admin & Legal | B22: =Assumptions!$B$29 | C22: =Assumptions!$B$29 | D22: =Assumptions!$B$29 | E22: =Assumptions!$B$29 | F22: =Assumptions!$B$29 | G22: =Assumptions!$B$29 | H22: =Assumptions!$B$29 | I22: =Assumptions!$B$29 | ... Y22: =Assumptions!$B$29 | Z22: =SUM(B22:Y22)
A23: Subtotal Expenses | B23: =SUM(B16:B22) | C23: =SUM(C16:C22) | D23: =SUM(D16:D22) | E23: =SUM(E16:E22) | F23: =SUM(F16:F22) | G23: =SUM(G16:G22) | H23: =SUM(H16:H22) | I23: =SUM(I16:I22) | ... Y23: =SUM(Y16:Y22) | Z23: =SUM(B23:Y23)
A24: Buffer | B24: =B23*Assumptions!$B$30 | C24: =C23*Assumptions!$B$30 | D24: =D23*Assumptions!$B$30 | E24: =E23*Assumptions!$B$30 | F24: =F23*Assumptions!$B$30 | G24: =G23*Assumptions!$B$30 | H24: =H23*Assumptions!$B$30 | I24: =I23*Assumptions!$B$30 | ... Y24: =Y23*Assumptions!$B$30 | Z24: =SUM(B24:Y24)
A25: TOTAL EXPENSES | B25: =B23+B24 | C25: =C23+C24 | D25: =D23+D24 | E25: =E23+E24 | F25: =F23+F24 | G25: =G23+G24 | H25: =H23+H24 | I25: =I23+I24 | ... Y25: =Y23+Y24 | Z25: =SUM(B25:Y25)
A27: CASH FLOW
A28: Net Cashflow | B28: =B9-B25 | C28: =C9-C25 | D28: =D9-D25 | E28: =E9-E25 | F28: =F9-F25 | G28: =G9-G25 | H28: =H9-H25 | I28: =I9-I25 | ... Y28: =Y9-Y25 | Z28: =SUM(B28:Y28)
A29: Cash Balance | B29: =Assumptions!$B$5+B28 | C29: =B29+C28 | D29: =C29+D28 | E29: =D29+E28 | F29: =E29+F28 | G29: =F29+G28 | H29: =G29+H28 | I29: =H29+I28 | J29: =I29+J28 | ... Y29: =X29+Y28 | Z29: =Y29
A31: KEY METRICS
A32: Runway (months) | B32: =IF(B25>0,B29/B25,999) | C32: =IF(C25>0,C29/C25,999) | D32: =IF(D25>0,D29/D25,999) | E32: =IF(E25>0,E29/E25,999) | F32: =IF(F25>0,F29/F25,999) | G32: =IF(G25>0,G29/G25,999) | H32: =IF(H25>0,H29/H25,999) | I32: =IF(I25>0,I29/I25,999) | ... Y32: =IF(Y25>0,Y29/Y25,999)
A33: Monthly Burn | B33: =IF(B28<0,-B28,0) | C33: =IF(C28<0,-C28,0) | D33: =IF(D28<0,-D28,0) | E33: =IF(E28<0,-E28,0) | F33: =IF(F28<0,-F28,0) | G33: =IF(G28<0,-G28,0) | H33: =IF(H28<0,-H28,0) | I33: =IF(I28<0,-I28,0) | ... Y33: =IF(Y28<0,-Y28,0) | Z33: =SUM(B33:Y33)
A35: LOWEST CASH POINT: | B35: =MIN(B29:Y29)
A36: MAX CAPITAL USED: | B36: =Assumptions!$B$5-MIN(B29:Y29)
